_mechanism_configuration.cp38-win32.pyd
lib/mechanism_configuration.lib
mechanism_configuration/__init__.py
mechanism_configuration/_version.py
mechanism_configuration/CMakeLists.txt
mechanism_configuration/tests/test_parser.py
mechanism_configuration/types.py
mechanism_configuration/wrapper.cpp
mechanism_configuration-0.2.0.dist-info/METADATA
mechanism_configuration-0.2.0.dist-info/WHEEL
mechanism_configuration-0.2.0.dist-info/licenses/LICENSE
mechanism_configuration-0.2.0.dist-info/RECORD
