Metadata-Version: 2.2
Name: mechanism_configuration
Version: 0.2.0
Summary: Mechanism Configuration is a library for managing chemical mechanisms in atmospheric models.
Author-Email: Matthew Dawsom <mattdawson@ucar.edu>, Kyle Shores <kshores@ucar.edu>
Maintainer-Email: ACOM MUSICA Developers <musica-support@ucar.edu>
License:                                  Apache License
Project-URL: homepage, https://ncar.github.io/MechanismConfiguration/
Provides-Extra: test
Requires-Dist: pytest; extra == "test"
